wgmgr/__init__.py
wgmgr/base.py
wgmgr/cli/__init__.py
wgmgr/cli/common.py
wgmgr/cli/p2p.py
wgmgr/cli/peer.py
wgmgr/error.py
wgmgr/keygen.py
wgmgr/migrations/__init__.py
wgmgr/operations/__init__.py
wgmgr/operations/config.py
wgmgr/operations/p2p.py
wgmgr/operations/peer.py
wgmgr/p2p.py
wgmgr/peer.py
wgmgr/site.py
wgmgr/templates/__init__.py
wgmgr/templates/graph.dot.j2
wgmgr/templates/wg-quick.conf.j2
wgmgr/util.py
wgmgr-0.3.0.dist-info/entry_points.txt
wgmgr-0.3.0.dist-info/LICENSE.md
wgmgr-0.3.0.dist-info/WHEEL
wgmgr-0.3.0.dist-info/METADATA
wgmgr-0.3.0.dist-info/RECORD
